am_parser/__init__.py
am_parser/parser.py
am_parser-1.0.19.dist-info/LICENSE
am_parser-1.0.19.dist-info/METADATA
am_parser-1.0.19.dist-info/WHEEL
am_parser-1.0.19.dist-info/top_level.txt
am_parser-1.0.19.dist-info/RECORD
