Metadata-Version: 2.1
Name: am-parser
Version: 1.0.19
Summary: Simple asciimath parser
Author: casual-aimer
License: GNU GPLv3
Platform: any
Requires-Python: >=3.9
License-File: LICENSE
